gnomish_army_knife/__init__.py
gnomish_army_knife/__main__.py
gnomish_army_knife/app.py
gnomish_army_knife/dev_requirements.txt
gnomish_army_knife/entry.py
gnomish_army_knife/py.typed
gnomish_army_knife/requirements.txt
gnomish_army_knife/schemas.py
gnomish_army_knife/commands/__init__.py
gnomish_army_knife/commands/all.py
gnomish_army_knife/commands/markdown.py
gnomish_army_knife/commands/scan.py
gnomish_army_knife/config/__init__.py
gnomish_army_knife/data/base.yaml
gnomish_army_knife/data/factories.yaml
gnomish_army_knife/data/macros.yaml
gnomish_army_knife/data/server.yaml
gnomish_army_knife/data/writer.yaml
gnomish_army_knife/data/_wow/abilities/druid/base.yaml
gnomish_army_knife/data/_wow/abilities/druid/feral.yaml
gnomish_army_knife/data/_wow/abilities/priest/base.yaml
gnomish_army_knife/data/_wow/abilities/priest/discipline.yaml
gnomish_army_knife/data/_wow/auras/evoker.yaml
gnomish_army_knife/data/_wow/backups/BetterBlizzFrames/full_profile.txt
gnomish_army_knife/data/_wow/backups/BetterBlizzPlates/full_profile.txt
gnomish_army_knife/data/_wow/backups/Details!/profile.txt
gnomish_army_knife/data/_wow/binds/bars.yaml
gnomish_army_knife/data/_wow/binds/class_template.yaml
gnomish_army_knife/data/_wow/binds/menus.yaml
gnomish_army_knife/data/_wow/binds/druid/feral.yaml
gnomish_army_knife/data/_wow/binds/priest/discipline.yaml
gnomish_army_knife/data/_wow/layouts/xbox_controller_ultrawide.txt
gnomish_army_knife/data/md/Macro.md
gnomish_army_knife/data/md/MacroCategory.md
gnomish_army_knife/data/md/MacroDatabase.md
gnomish_army_knife/data/md/MacroGroup.md
gnomish_army_knife/data/schemas/CombatLogFile.yaml
gnomish_army_knife/data/schemas/CombatLogState.yaml
gnomish_army_knife/data/schemas/Config.yaml
gnomish_army_knife/data/schemas/Macro.yaml
gnomish_army_knife/data/schemas/MacroCategory.yaml
gnomish_army_knife/data/schemas/MacroDatabase.yaml
gnomish_army_knife/data/schemas/MacroGroup.yaml
gnomish_army_knife/data/schemas/has_icon.yaml
gnomish_army_knife-1.5.7.dist-info/LICENSE
gnomish_army_knife-1.5.7.dist-info/METADATA
gnomish_army_knife-1.5.7.dist-info/WHEEL
gnomish_army_knife-1.5.7.dist-info/entry_points.txt
gnomish_army_knife-1.5.7.dist-info/top_level.txt
gnomish_army_knife-1.5.7.dist-info/RECORD
