Metadata-Version: 2.2
Name: gnomish-army-knife
Version: 1.5.7
Summary: World of Warcraft polyfills and standardization.
Home-page: https://github.com/vkottler/gnomish-army-knife
Author: Vaughn Kottler
Author-email: Vaughn Kottler <vaughn@libre-embedded.com>
Maintainer-email: Vaughn Kottler <vaughn@libre-embedded.com>
Classifier: Programming Language :: Python :: 3.12
Classifier: Programming Language :: Python :: 3.13
Classifier: Operating System :: Microsoft :: Windows
Classifier: Operating System :: MacOS
Classifier: Operating System :: POSIX :: Linux
Classifier: Operating System :: Unix
Classifier: Development Status :: 5 - Production/Stable
Classifier: License :: OSI Approved :: MIT License
Requires-Python: >=3.12
License-File: LICENSE
Requires-Dist: runtimepy>=5.10.1
Requires-Dist: vcorelib>=3.5.0
Provides-Extra: test
Requires-Dist: pylint; extra == "test"
Requires-Dist: flake8; extra == "test"
Requires-Dist: black; extra == "test"
Requires-Dist: ruff; extra == "test"
Requires-Dist: mypy; extra == "test"
Requires-Dist: isort; extra == "test"
Requires-Dist: yamllint; extra == "test"
Requires-Dist: yambs; extra == "test"
Requires-Dist: vmklib>=2.0.3; extra == "test"
Requires-Dist: sphinx; extra == "test"
Requires-Dist: sphinx-book-theme; extra == "test"
Requires-Dist: setuptools-wrapper; extra == "test"
Requires-Dist: types-setuptools; extra == "test"
Dynamic: author
Dynamic: home-page
Dynamic: requires-dist
Dynamic: requires-python
